astrobasecloud/__init__.py
astrobasecloud/py.typed
astrobasecloud/cli/__init__.py
astrobasecloud/cli/aks.py
astrobasecloud/cli/cluster.py
astrobasecloud/cli/config.py
astrobasecloud/cli/eks.py
astrobasecloud/cli/gke.py
astrobasecloud/cli/main.py
astrobasecloud/cli/profile.py
astrobasecloud/cli/provider.py
astrobasecloud/cli/setup.py
astrobasecloud/exc/__init__.py
astrobasecloud/exc/main.py
astrobasecloud/providers/__init__.py
astrobasecloud/providers/_provider.py
astrobasecloud/providers/aws.py
astrobasecloud/providers/azure.py
astrobasecloud/providers/gcp.py
astrobasecloud/providers/main.py
astrobasecloud/server/__init__.py
astrobasecloud/server/config.py
astrobasecloud/server/gunicorn_config.py
astrobasecloud/server/logger.py
astrobasecloud/server/main.py
astrobasecloud/server/routers/__init__.py
astrobasecloud/server/routers/aws.py
astrobasecloud/server/routers/azure.py
astrobasecloud/server/routers/gcp.py
astrobasecloud/server/routers/health.py
astrobasecloud/types/__init__.py
astrobasecloud/types/aws.py
astrobasecloud/types/azure.py
astrobasecloud/types/gcp.py
astrobasecloud/types/health.py
astrobasecloud/types/provider.py
astrobasecloud/utils/__init__.py
astrobasecloud/utils/str_to_dict.py
astrobasecloud-0.2.4.dist-info/entry_points.txt
astrobasecloud-0.2.4.dist-info/LICENSE
astrobasecloud-0.2.4.dist-info/WHEEL
astrobasecloud-0.2.4.dist-info/METADATA
astrobasecloud-0.2.4.dist-info/RECORD
