Metadata-Version: 2.1
Name: astrobasecloud
Version: 0.2.4
Summary: astrobase
Author-email: "Astrobase Inc." <anthony@astrobase.cloud>
Requires-Python: >=3.7.5
Classifier: Intended Audience :: Information Technology
Classifier: Intended Audience :: System Administrators
Classifier: Operating System :: OS Independent
Classifier: Programming Language :: Python :: 3
Classifier: Programming Language :: Python
Classifier: Topic :: Internet
Classifier: Topic :: Software Development :: Libraries :: Python Modules
Classifier: Topic :: Software Development :: Libraries
Classifier: Topic :: Software Development
Classifier: Typing :: Typed
Classifier: Development Status :: 4 - Beta
Classifier: Environment :: Web Environment
Classifier: Framework :: AsyncIO
Classifier: Framework :: FastAPI
Classifier: Intended Audience :: Developers
Classifier: License :: OSI Approved :: MIT License
Classifier: Programming Language :: Python :: 3 :: Only
Classifier: Programming Language :: Python :: 3.7
Classifier: Programming Language :: Python :: 3.8
Classifier: Programming Language :: Python :: 3.9
Classifier: Programming Language :: Python :: 3.10
Classifier: Topic :: Internet :: WWW/HTTP :: HTTP Servers
Classifier: Topic :: Internet :: WWW/HTTP
Requires-Dist: fastapi>=0.74.0
Requires-Dist: typer>=0.4.0
Requires-Dist: gunicorn>=20.1.0
Requires-Dist: uvicorn>=0.17.0
Requires-Dist: PyYaml>=6.0
Requires-Dist: google-cloud-container>=2.10.3
Requires-Dist: google-cloud-service-usage>=1.2.1
Requires-Dist: boto3>=1.17.22
Requires-Dist: azure-identity>=1.7.1
Requires-Dist: azure-mgmt-resource>=20.1.0
Requires-Dist: azure-mgmt-containerservice>=17.0.0
Requires-Dist: msrestazure>=0.6.4
Requires-Dist: flake8>=4.0.1 ; extra == "dev"
Requires-Dist: black>=21.12b0 ; extra == "dev"
Requires-Dist: isort>=5.10.1 ; extra == "dev"
Requires-Dist: autoflake>=1.4 ; extra == "dev"
Requires-Dist: flake8-docstrings>=1.6.0 ; extra == "dev"
Requires-Dist: mkdocs>=1.1.2,<2.0.0 ; extra == "doc"
Requires-Dist: mkdocs-material>=8.1.4,<9.0.0 ; extra == "doc"
Requires-Dist: mdx-include>=1.4.1,<2.0.0 ; extra == "doc"
Requires-Dist: pytest>=6.2.5 ; extra == "test"
Requires-Dist: mypy>=0.910 ; extra == "test"
Requires-Dist: coverage>=6.2 ; extra == "test"
Requires-Dist: pytest-cov>=3.0.0 ; extra == "test"
Requires-Dist: requests-mock>=1.9.3 ; extra == "test"
Requires-Dist: types-PyYAML>=6.0.3 ; extra == "test"
Requires-Dist: types-requests>=2.27.8 ; extra == "test"
Project-URL: Documentation, https://docs.astrobase.cloud
Project-URL: Home, https://www.github.com/astrobase/astrobase
Provides-Extra: dev
Provides-Extra: doc
Provides-Extra: test
